setup.py
wsgi_supervisor/__init__.py
wsgi_supervisor/server.py
wsgi_supervisor/supervisor.py
wsgi_supervisor.egg-info/PKG-INFO
wsgi_supervisor.egg-info/SOURCES.txt
wsgi_supervisor.egg-info/dependency_links.txt
wsgi_supervisor.egg-info/entry_points.txt
wsgi_supervisor.egg-info/requires.txt
wsgi_supervisor.egg-info/top_level.txt