Metadata-Version: 1.0
Name: wsgi-supervisor
Version: 0.0.2
Summary: reload wsgi app on file change
Home-page: https://github.com/zweifisch/wsgi-supervisor
Author: Feng Zhou
Author-email: zf.pascal@gmail.com
License: UNKNOWN
Platform: UNKNOWN
